odoo/addons/mrp_finished_backorder_product/README.rst
odoo/addons/mrp_finished_backorder_product/__init__.py
odoo/addons/mrp_finished_backorder_product/__manifest__.py
odoo/addons/mrp_finished_backorder_product/i18n/it.po
odoo/addons/mrp_finished_backorder_product/i18n/mrp_finished_backorder_product.pot
odoo/addons/mrp_finished_backorder_product/models/__init__.py
odoo/addons/mrp_finished_backorder_product/models/mrp_production.py
odoo/addons/mrp_finished_backorder_product/readme/CONTRIBUTORS.rst
odoo/addons/mrp_finished_backorder_product/readme/DESCRIPTION.rst
odoo/addons/mrp_finished_backorder_product/static/description/icon.png
odoo/addons/mrp_finished_backorder_product/static/description/index.html
odoo/addons/mrp_finished_backorder_product/views/mrp_production_views.xml
odoo_addon_mrp_finished_backorder_product-15.0.1.0.0.6.dist-info/METADATA
odoo_addon_mrp_finished_backorder_product-15.0.1.0.0.6.dist-info/WHEEL
odoo_addon_mrp_finished_backorder_product-15.0.1.0.0.6.dist-info/top_level.txt
odoo_addon_mrp_finished_backorder_product-15.0.1.0.0.6.dist-info/RECORD
